efb_parabox_master/__init__.py
efb_parabox_master/__version__.py
efb_parabox_master/chat.py
efb_parabox_master/chat_object_cache.py
efb_parabox_master/constants.py
efb_parabox_master/db.py
efb_parabox_master/fcm_client.py
efb_parabox_master/fcm_util.py
efb_parabox_master/master_message.py
efb_parabox_master/message.py
efb_parabox_master/qiniu_util.py
efb_parabox_master/server.py
efb_parabox_master/slave_message.py
efb_parabox_master/tencent_cos_util.py
efb_parabox_master/utils.py
efb_parabox_master/wizard.py
efb_parabox_master/xmpp.py
efb_parabox_master/xmpp_backup.py
efb_parabox_master-1.0.5.dist-info/LICENSE
efb_parabox_master-1.0.5.dist-info/METADATA
efb_parabox_master-1.0.5.dist-info/WHEEL
efb_parabox_master-1.0.5.dist-info/entry_points.txt
efb_parabox_master-1.0.5.dist-info/top_level.txt
efb_parabox_master-1.0.5.dist-info/RECORD
